olallieberry/__init__.py
olallieberry/lexer.py
olallieberry/rule.py
olallieberry/token.py
olallieberry-1.0.0.dist-info/LICENSE
olallieberry-1.0.0.dist-info/METADATA
olallieberry-1.0.0.dist-info/WHEEL
olallieberry-1.0.0.dist-info/RECORD
